[{"MID":102.0,"VID":102.0,"COMPANY":"3rd Company","VALUE":"3rd Company","UNUSED":0.0},{"MID":101.0,"VID":101.0,"COMPANY":"UI Company","VALUE":"UI Company","UNUSED":1.0},{"MID":161.0,"VID":161.0,"COMPANY":"Firma_neu","VALUE":"Firma_neu","UNUSED":0.0},{"MID":162.0,"VID":162.0,"COMPANY":"Firma_I","VALUE":"Firma_I","UNUSED":0.0},{"MID":201.0,"VID":201.0,"COMPANY":"Bauunternehmen XYZ","VALUE":"Bauunternehmen XYZ","UNUSED":0.0},{"MID":121.0,"VID":121.0,"COMPANY":"Neue Firma","VALUE":"Neue Firma","UNUSED":0.0},{"MID":182.0,"VID":182.0,"COMPANY":"Testupdate 2 company Inc.","VALUE":"Testupdate 2 company Inc.","UNUSED":0.0},{"MID":241.0,"VID":241.0,"COMPANY":"Doolittle","VALUE":"Doolittle","UNUSED":0.0},{"MID":281.0,"VID":281.0,"COMPANY":"Another One Inc.","VALUE":"Another One Inc.","UNUSED":0.0},{"MID":341.0,"VID":341.0,"COMPANY":"COMP_JM0","VALUE":"COMP_JM0","UNUSED":0.0},{"MID":1.0,"VID":1.0,"COMPANY":"Public Company","VALUE":"Public Company","UNUSED":0.0},{"MID":381.0,"VID":381.0,"COMPANY":"Tester company Ltd.","VALUE":"Tester company Ltd.","UNUSED":0.0},{"MID":301.0,"VID":301.0,"COMPANY":"Tester company Ltd.","VALUE":"Tester company Ltd.","UNUSED":0.0},{"MID":401.0,"VID":401.0,"COMPANY":null,"VALUE":null,"UNUSED":null},{"MID":421.0,"VID":421.0,"COMPANY":"Power System a.s.","VALUE":"Power System a.s.","UNUSED":0.0},{"MID":321.0,"VID":321.0,"COMPANY":"Tester company Ltd.","VALUE":"Tester company Ltd.","UNUSED":0.0}]